openobd_utils/__init__.py
openobd_utils/_metadata.py
openobd_utils/connection_monitor.py
openobd_utils/function_context_handler.py
openobd_utils/function_exceptions.py
openobd_utils/isotp_socket.py
openobd_utils/kline_socket.py
openobd_utils/raw_socket.py
openobd_utils/response_exceptions.py
openobd_utils/session_token_handler.py
openobd_utils/stream_exceptions.py
openobd_utils/stream_handler.py
openobd_utils/terminal15_socket.py
openobd_utils/ui_handler.py
openobd_utils-1.18.20.dist-info/licenses/LICENSE
openobd_utils-1.18.20.dist-info/METADATA
openobd_utils-1.18.20.dist-info/WHEEL
openobd_utils-1.18.20.dist-info/top_level.txt
openobd_utils-1.18.20.dist-info/RECORD
