Metadata-Version: 2.4
Name: openobd-utils
Version: 1.18.20
Summary: Jifeline Networks openOBD Python Utils Library
Author-email: Gerhard de Koning Gans <gerhard@factorit.nl>, Wessel van Tunen <wessel@factorit.nl>, Rohaan Ghosh <rohaan@factorit.nl>, Sander de Mooij <sanderdemooij@factorit.nl>
Maintainer-email: Gerhard de Koning Gans <gerhard@factorit.nl>, Wessel van Tunen <wessel@factorit.nl>, Rohaan Ghosh <rohaan@factorit.nl>, Sander de Mooij <sanderdemooij@factorit.nl>
License: Copyright (c) 2024 Jifeline Networks B.V.
Project-URL: Homepage, https://www.openobd.com
Keywords: openOBD,Protocol,gRPC,Jifeline,Remote,Diagnostics,OBD,On-board,Automotive,Car,Vehicle,CAN,K-line,DoIP
Platform: any
Classifier: Development Status :: 4 - Beta
Classifier: License :: OSI Approved :: MIT License
Classifier: Operating System :: OS Independent
Classifier: Programming Language :: Python :: 3
Classifier: Topic :: Communications
Requires-Python: >=3.11
License-File: LICENSE
Requires-Dist: openobd==1.18.19rc0
Dynamic: license-file
